README.rst
nameko_sentry.py
setup.py
nameko_sentry.egg-info/PKG-INFO
nameko_sentry.egg-info/SOURCES.txt
nameko_sentry.egg-info/dependency_links.txt
nameko_sentry.egg-info/requires.txt
nameko_sentry.egg-info/top_level.txt
nameko_sentry.egg-info/zip-safe