Metadata-Version: 1.1
Name: nameko-sentry
Version: 0.0.2
Summary: Nameko extension sends entrypoint exceptions to sentry
Home-page: http://github.com/mattbennett/nameko-sentry
Author: Matt Bennett
Author-email: matt@bennett.name
License: Apache License, Version 2.0
Platform: UNKNOWN
Classifier: Programming Language :: Python
Classifier: Operating System :: MacOS :: MacOS X
Classifier: Operating System :: POSIX
Classifier: Programming Language :: Python :: 2
Classifier: Programming Language :: Python :: 2.7
Classifier: Programming Language :: Python :: 3
Classifier: Programming Language :: Python :: 3.3
Classifier: Programming Language :: Python :: 3.4
Classifier: Topic :: Internet
Classifier: Topic :: Software Development :: Libraries :: Python Modules
Classifier: Intended Audience :: Developers
